hammadPyCore/__init__.py
hammadPyCore/hammadpycore.py
hammadPyCore/data/__init__.py
hammadPyCore/data/dataframe.py
hammadPyCore/interactions/__init__.py
hammadPyCore/interactions/inputs.py
hammadPyCore/interactions/messages.py
hammadPyCore/interactions/status.py
hammadPyCore/verifiers/__init__.py
hammadPyCore/verifiers/verifiers.py
hammadPyCore-0.1.42.1.dist-info/METADATA
hammadPyCore-0.1.42.1.dist-info/WHEEL
hammadPyCore-0.1.42.1.dist-info/top_level.txt
hammadPyCore-0.1.42.1.dist-info/RECORD
