Metadata-Version: 2.1
Name: hammadPyCore
Version: 0.1.42.1
Summary: Hammad's Python Tools -- Core Library
Author: Hammad Saeed
Author-email: hammad@supportvectors.com
Classifier: Programming Language :: Python :: 3
Classifier: License :: OSI Approved :: MIT License
Classifier: Operating System :: OS Independent
Requires-Python: >=3.10
Requires-Dist: colorama ==0.4.6
Requires-Dist: numpy ==1.26.4
Requires-Dist: pandas ==2.2.0
Requires-Dist: prompt-toolkit ==3.0.43
Requires-Dist: python-dateutil ==2.8.2
Requires-Dist: pytz ==2024.1
Requires-Dist: six ==1.16.0
Requires-Dist: tzdata ==2024.1
Requires-Dist: wcwidth ==0.2.13
